README
qct
setup.py
qct.egg-info/PKG-INFO
qct.egg-info/SOURCES.txt
qct.egg-info/dependency_links.txt
qct.egg-info/top_level.txt
qctlib/__init__.py
qctlib/gui_logic.py
qctlib/ui_dialog.py
qctlib/ui_preferences.py
qctlib/utils.py
qctlib/vcs/__init__.py
qctlib/vcs/bzr.py
qctlib/vcs/cvs.py
qctlib/vcs/git.py
qctlib/vcs/hg.py
qctlib/vcs/mtn.py
qctlib/vcs/p4.py
