Metadata-Version: 1.0
Name: qct
Version: 0.8
Summary: Commit Tool
Home-page: http://hg.borho.org/qct
Author: Steve Borho
Author-email: steve@borho.org
License: GNU GPL2
Download-URL: http://www.borho.org/~steve/qct-0.8-py2.4.egg
Platform: All
Classifier: Development Status :: 4 - Beta
Classifier: License :: OSI Approved :: GNU General Public License (GPL)
Classifier: Intended Audience :: Developers
Classifier: Intended Audience :: Science/Research
Classifier: Intended Audience :: System Administrators
Classifier: Natural Language :: English
Classifier: Environment :: Console
Classifier: Environment :: MacOS X
Classifier: Operating System :: OS Independent
Classifier: Operating System :: Microsoft :: Windows
Classifier: Operating System :: POSIX
Classifier: Operating System :: Unix
Classifier: Programming Language :: Python
Classifier: Topic :: Software Development
Classifier: Topic :: System :: Systems Administration
Classifier: Topic :: Software Development :: Version Control
